_chronomeleon_version.py
chronomeleon/__init__.py
chronomeleon/mapping.py
chronomeleon/py.typed
chronomeleon/models/__init__.py
chronomeleon/models/chrono_assumption.py
chronomeleon/models/mapping_config.py
chronomeleon-0.1.3.dist-info/METADATA
chronomeleon-0.1.3.dist-info/WHEEL
chronomeleon-0.1.3.dist-info/licenses/LICENSE
chronomeleon-0.1.3.dist-info/RECORD
