Metadata-Version: 2.3
Name: chronomeleon
Version: 0.1.3
Summary: A python package to flexibly adapt start and end date(times) to your system background
Project-URL: Changelog, https://github.com/Hochfrequenz/chronomeleon/releases
Project-URL: Homepage, https://github.com/Hochfrequenz/chronomeleon
Author-email: Hochfrequenz Unternehmensberatung GmbH <info+github@hochfrequenz.de>
License: MIT
License-File: LICENSE
Keywords: conversion,date,dateonly,exclusive,inclusive,migration,time
Classifier: Development Status :: 4 - Beta
Classifier: Environment :: Console
Classifier: Intended Audience :: Developers
Classifier: License :: OSI Approved :: MIT License
Classifier: Operating System :: OS Independent
Classifier: Programming Language :: Python
Classifier: Programming Language :: Python :: 3 :: Only
Classifier: Programming Language :: Python :: 3.10
Classifier: Programming Language :: Python :: 3.11
Classifier: Programming Language :: Python :: 3.12
Classifier: Programming Language :: Python :: 3.13
Requires-Python: >=3.10
Requires-Dist: pytz
Provides-Extra: coverage
Requires-Dist: coverage==7.6.1; extra == 'coverage'
Provides-Extra: formatting
Requires-Dist: black==24.8.0; extra == 'formatting'
Requires-Dist: isort==5.13.2; extra == 'formatting'
Provides-Extra: linting
Requires-Dist: pylint==3.3.1; extra == 'linting'
Provides-Extra: spellcheck
Requires-Dist: codespell==2.3.0; extra == 'spellcheck'
Provides-Extra: test-packaging
Requires-Dist: build==1.2.2.post1; extra == 'test-packaging'
Requires-Dist: twine==5.1.1; extra == 'test-packaging'
Provides-Extra: tests
Requires-Dist: pytest==8.3.3; extra == 'tests'
Provides-Extra: type-check
Requires-Dist: mypy==1.11.2; extra == 'type-check'
Requires-Dist: types-pytz==2024.2.0.20241003; extra == 'type-check'
